ionbench/__init__.py
ionbench/benchmarker/__init__.py
ionbench/benchmarker/benchmarker.py
ionbench/data/loewe2016/courtemanche-1998-ikr.mmt
ionbench/data/loewe2016/courtemanche-1998-ikur.mmt
ionbench/data/loewe2016/ikr.csv
ionbench/data/loewe2016/ikur.csv
ionbench/data/moreno2016/ina.csv
ionbench/data/moreno2016/moreno2016.mmt
ionbench/data/staircase/beattie-2017-ikr-hh.mmt
ionbench/data/staircase/dataHH.csv
ionbench/data/staircase/dataMM.csv
ionbench/data/staircase/fink-2008-ikr-mm.mmt
ionbench/data/staircase/staircase-pace.mmt
ionbench/data/test/data.csv
ionbench/modification/__init__.py
ionbench/modification/modification.py
ionbench/optimisers/__init__.py
ionbench/optimisers/external_optimisers/DE_Zhou2009.py
ionbench/optimisers/external_optimisers/GA_Bot2012.py
ionbench/optimisers/external_optimisers/GA_Cairns2017.py
ionbench/optimisers/external_optimisers/GA_Gurkiewicz2007a.py
ionbench/optimisers/external_optimisers/GA_Gurkiewicz2007b.py
ionbench/optimisers/external_optimisers/GA_Smirnov2020.py
ionbench/optimisers/external_optimisers/NMPSO_Clausen2020.py
ionbench/optimisers/external_optimisers/NMPSO_Liu2011.py
ionbench/optimisers/external_optimisers/PSOTRR_Loewe2016.py
ionbench/optimisers/external_optimisers/PSO_Loewe2016.py
ionbench/optimisers/external_optimisers/SA_Vanier1999.py
ionbench/optimisers/external_optimisers/SPSA_Spall1998.py
ionbench/optimisers/external_optimisers/__init__.py
ionbench/optimisers/external_optimisers/curvilinearGD_Dokos2004.py
ionbench/optimisers/external_optimisers/hybridPSOTRRTRR_Loewe2016.py
ionbench/optimisers/external_optimisers/hybridPSOTRR_Loewe2016.py
ionbench/optimisers/external_optimisers/patternSearch_Kohjitani2022.py
ionbench/optimisers/external_optimisers/ppso_Chen2012.py
ionbench/optimisers/external_optimisers/pso_Cabo2022.py
ionbench/optimisers/external_optimisers/pso_Seemann2009.py
ionbench/optimisers/external_optimisers/randomSearch_Vanier1999.py
ionbench/optimisers/external_optimisers/stochasticSearch_Vanier1999.py
ionbench-1.0.1.dist-info/licenses/LICENSE.txt
ionbench-1.0.1.dist-info/METADATA
ionbench-1.0.1.dist-info/WHEEL
ionbench-1.0.1.dist-info/top_level.txt
ionbench-1.0.1.dist-info/RECORD
