Metadata-Version: 2.4
Name: ionbench
Version: 1.0.1
Summary: A benchmarking tool for comparing different parameter optimization algorithms for ion channel models
Home-page: https://github.com/CardiacModelling/ionbench
Author: Matt J. Owen
Author-email: matt.owen@bristol.ac.uk
Project-URL: Bug Reports, https://github.com/CardiacModelling/ionbench/issues
Project-URL: Source, https://github.com/CardiacModelling/ionbench
Classifier: Development Status :: 5 - Production/Stable
Classifier: Intended Audience :: Science/Research
Classifier: Topic :: Scientific/Engineering :: Bio-Informatics
Classifier: License :: OSI Approved :: BSD License
Requires-Python: >=3.9, <4
License-File: LICENSE.txt
Requires-Dist: numpy
Requires-Dist: pandas
Requires-Dist: scipy
Requires-Dist: pints>=0.4.1
Requires-Dist: myokit>=1.36.0
Requires-Dist: matplotlib>=3.7.1
Requires-Dist: mygrad>=2.2.0
Requires-Dist: pymoo>=0.6.0.1
Dynamic: author
Dynamic: author-email
Dynamic: classifier
Dynamic: description
Dynamic: description-content-type
Dynamic: home-page
Dynamic: license-file
Dynamic: project-url
Dynamic: requires-dist
Dynamic: requires-python
Dynamic: summary
